<?xml version='1.0' encoding='UTF-8'?>
<?artifactRepository version='1.1.0'?>
<repository name='/folk/wb/working_qf/vx692wb3322/r_r_wb16.12sp/docs/extensions' type='org.eclipse.equinox.p2.artifact.repository.simpleRepository' version='1.0.0'>
  <properties size='1'>
    <property name='p2.timestamp' value='1334799077912'/>
  </properties>
  <mappings size='3'>
    <rule filter='(&amp; (classifier=osgi.bundle))' output='${repoUrl}/plugins/${id}_${version}.jar'/>
    <rule filter='(&amp; (classifier=binary))' output='${repoUrl}/binary/${id}_${version}'/>
    <rule filter='(&amp; (classifier=org.eclipse.update.feature))' output='${repoUrl}/features/${id}_${version}.jar'/>
  </mappings>
  <artifacts size='33'>
    <artifact classifier='osgi.bundle' id='com.windriver.ide.doc.wr_tipc_1.7.7' version='1.7.7'>
      <properties size='2'>
        <property name='artifact.size' value='4096'/>
        <property name='download.size' value='4096'/>
      </properties>
      <repositoryProperties size='3'>
        <property name='artifact.folder' value='true'/>
        <property name='artifact.reference' value='file:/folk/wb/working_qf/vx692wb3322/r_r_wb16.12sp/docs/extensions/eclipse/plugins/com.windriver.ide.doc.wr_tipc_1.7.7/'/>
        <property name='file.name' value='/folk/wb/working_qf/vx692wb3322/r_r_wb16.12sp/docs/extensions/eclipse/plugins/com.windriver.ide.doc.wr_tipc_1.7.7'/>
      </repositoryProperties>
    </artifact>
    <artifact classifier='osgi.bundle' id='com.windriver.ide.doc.wr_workbench_linux' version='3.3.0'>
      <properties size='2'>
        <property name='artifact.size' value='4096'/>
        <property name='download.size' value='4096'/>
      </properties>
      <repositoryProperties size='3'>
        <property name='artifact.folder' value='true'/>
        <property name='artifact.reference' value='file:/folk/wb/working_qf/vx692wb3322/r_r_wb16.12sp/docs/extensions/eclipse/plugins/com.windriver.ide.doc.wr_workbench_linux_tooling_3.3/'/>
        <property name='file.name' value='/folk/wb/working_qf/vx692wb3322/r_r_wb16.12sp/docs/extensions/eclipse/plugins/com.windriver.ide.doc.wr_workbench_linux_tooling_3.3'/>
      </repositoryProperties>
    </artifact>
    <artifact classifier='osgi.bundle' id='com.windriver.ide.doc.wr_workbench_memory_analyzer' version='3.3.0'>
      <properties size='2'>
        <property name='artifact.size' value='4096'/>
        <property name='download.size' value='4096'/>
      </properties>
      <repositoryProperties size='3'>
        <property name='artifact.folder' value='true'/>
        <property name='artifact.reference' value='file:/folk/wb/working_qf/vx692wb3322/r_r_wb16.12sp/docs/extensions/eclipse/plugins/com.windriver.ide.doc.wr_workbench_memory_analyzer_tooling_3.3/'/>
        <property name='file.name' value='/folk/wb/working_qf/vx692wb3322/r_r_wb16.12sp/docs/extensions/eclipse/plugins/com.windriver.ide.doc.wr_workbench_memory_analyzer_tooling_3.3'/>
      </repositoryProperties>
    </artifact>
    <artifact classifier='osgi.bundle' id='com.windriver.ide.doc.partners' version='1.0.0'>
      <properties size='2'>
        <property name='artifact.size' value='4096'/>
        <property name='download.size' value='4096'/>
      </properties>
      <repositoryProperties size='3'>
        <property name='artifact.folder' value='true'/>
        <property name='artifact.reference' value='file:/folk/wb/working_qf/vx692wb3322/r_r_wb16.12sp/docs/extensions/eclipse/plugins/com.windriver.ide.doc.partners/'/>
        <property name='file.name' value='/folk/wb/working_qf/vx692wb3322/r_r_wb16.12sp/docs/extensions/eclipse/plugins/com.windriver.ide.doc.partners'/>
      </repositoryProperties>
    </artifact>
    <artifact classifier='osgi.bundle' id='com.windriver.ide.doc.standard_ccplus_libraries' version='6.9.0'>
      <properties size='2'>
        <property name='artifact.size' value='4096'/>
        <property name='download.size' value='4096'/>
      </properties>
      <repositoryProperties size='3'>
        <property name='artifact.folder' value='true'/>
        <property name='artifact.reference' value='file:/folk/wb/working_qf/vx692wb3322/r_r_wb16.12sp/docs/extensions/eclipse/plugins/com.windriver.ide.doc.standard_ccplus_libraries_tooling_6.9/'/>
        <property name='file.name' value='/folk/wb/working_qf/vx692wb3322/r_r_wb16.12sp/docs/extensions/eclipse/plugins/com.windriver.ide.doc.standard_ccplus_libraries_tooling_6.9'/>
      </repositoryProperties>
    </artifact>
    <artifact classifier='osgi.bundle' id='com.windriver.ide.doc.wr_ppp_6.9' version='6.9.0'>
      <properties size='2'>
        <property name='artifact.size' value='4096'/>
        <property name='download.size' value='4096'/>
      </properties>
      <repositoryProperties size='3'>
        <property name='artifact.folder' value='true'/>
        <property name='artifact.reference' value='file:/folk/wb/working_qf/vx692wb3322/r_r_wb16.12sp/docs/extensions/eclipse/plugins/com.windriver.ide.doc.wr_ppp_6.9/'/>
        <property name='file.name' value='/folk/wb/working_qf/vx692wb3322/r_r_wb16.12sp/docs/extensions/eclipse/plugins/com.windriver.ide.doc.wr_ppp_6.9'/>
      </repositoryProperties>
    </artifact>
    <artifact classifier='osgi.bundle' id='com.windriver.ide.doc.intel_ipp_7.0' version='7.0.0'>
      <properties size='2'>
        <property name='artifact.size' value='4096'/>
        <property name='download.size' value='4096'/>
      </properties>
      <repositoryProperties size='3'>
        <property name='artifact.folder' value='true'/>
        <property name='artifact.reference' value='file:/folk/wb/working_qf/vx692wb3322/r_r_wb16.12sp/docs/extensions/eclipse/plugins/com.windriver.ide.doc.intel_ipp_7.0/'/>
        <property name='file.name' value='/folk/wb/working_qf/vx692wb3322/r_r_wb16.12sp/docs/extensions/eclipse/plugins/com.windriver.ide.doc.intel_ipp_7.0'/>
      </repositoryProperties>
    </artifact>
    <artifact classifier='osgi.bundle' id='com.windriver.ide.doc.wr_vx_simulator' version='6.9.0'>
      <properties size='2'>
        <property name='artifact.size' value='4096'/>
        <property name='download.size' value='4096'/>
      </properties>
      <repositoryProperties size='3'>
        <property name='artifact.folder' value='true'/>
        <property name='artifact.reference' value='file:/folk/wb/working_qf/vx692wb3322/r_r_wb16.12sp/docs/extensions/eclipse/plugins/com.windriver.ide.doc.wr_vx_simulator_tooling_6.9/'/>
        <property name='file.name' value='/folk/wb/working_qf/vx692wb3322/r_r_wb16.12sp/docs/extensions/eclipse/plugins/com.windriver.ide.doc.wr_vx_simulator_tooling_6.9'/>
      </repositoryProperties>
    </artifact>
    <artifact classifier='osgi.bundle' id='com.windriver.ide.doc.globals' version='3.3.0'>
      <properties size='2'>
        <property name='artifact.size' value='8192'/>
        <property name='download.size' value='8192'/>
      </properties>
      <repositoryProperties size='3'>
        <property name='artifact.folder' value='true'/>
        <property name='artifact.reference' value='file:/folk/wb/working_qf/vx692wb3322/r_r_wb16.12sp/docs/extensions/eclipse/plugins/com.windriver.ide.doc.globals_3.3/'/>
        <property name='file.name' value='/folk/wb/working_qf/vx692wb3322/r_r_wb16.12sp/docs/extensions/eclipse/plugins/com.windriver.ide.doc.globals_3.3'/>
      </repositoryProperties>
    </artifact>
    <artifact classifier='osgi.bundle' id='com.windriver.ide.doc.vxworks_6.9' version='6.9.0'>
      <properties size='2'>
        <property name='artifact.size' value='8192'/>
        <property name='download.size' value='8192'/>
      </properties>
      <repositoryProperties size='3'>
        <property name='artifact.folder' value='true'/>
        <property name='artifact.reference' value='file:/folk/wb/working_qf/vx692wb3322/r_r_wb16.12sp/docs/extensions/eclipse/plugins/com.windriver.ide.doc.vxworks_6.9/'/>
        <property name='file.name' value='/folk/wb/working_qf/vx692wb3322/r_r_wb16.12sp/docs/extensions/eclipse/plugins/com.windriver.ide.doc.vxworks_6.9'/>
      </repositoryProperties>
    </artifact>
    <artifact classifier='osgi.bundle' id='com.windriver.ide.doc.wr_diab_compiler_standalone_5.9' version='5.9.0'>
      <properties size='2'>
        <property name='artifact.size' value='4096'/>
        <property name='download.size' value='4096'/>
      </properties>
      <repositoryProperties size='3'>
        <property name='artifact.folder' value='true'/>
        <property name='artifact.reference' value='file:/folk/wb/working_qf/vx692wb3322/r_r_wb16.12sp/docs/extensions/eclipse/plugins/com.windriver.ide.doc.wr_diab_compiler_standalone_5.9/'/>
        <property name='file.name' value='/folk/wb/working_qf/vx692wb3322/r_r_wb16.12sp/docs/extensions/eclipse/plugins/com.windriver.ide.doc.wr_diab_compiler_standalone_5.9'/>
      </repositoryProperties>
    </artifact>
    <artifact classifier='osgi.bundle' id='com.windriver.ide.doc.wr_diab_compiler_5.9' version='5.9.0'>
      <properties size='2'>
        <property name='artifact.size' value='4096'/>
        <property name='download.size' value='4096'/>
      </properties>
      <repositoryProperties size='3'>
        <property name='artifact.folder' value='true'/>
        <property name='artifact.reference' value='file:/folk/wb/working_qf/vx692wb3322/r_r_wb16.12sp/docs/extensions/eclipse/plugins/com.windriver.ide.doc.wr_diab_compiler_5.9/'/>
        <property name='file.name' value='/folk/wb/working_qf/vx692wb3322/r_r_wb16.12sp/docs/extensions/eclipse/plugins/com.windriver.ide.doc.wr_diab_compiler_5.9'/>
      </repositoryProperties>
    </artifact>
    <artifact classifier='osgi.bundle' id='com.windriver.ide.doc.wr_system_viewer' version='3.3.0'>
      <properties size='2'>
        <property name='artifact.size' value='4096'/>
        <property name='download.size' value='4096'/>
      </properties>
      <repositoryProperties size='3'>
        <property name='artifact.folder' value='true'/>
        <property name='artifact.reference' value='file:/folk/wb/working_qf/vx692wb3322/r_r_wb16.12sp/docs/extensions/eclipse/plugins/com.windriver.ide.doc.wr_system_viewer_tooling_3.3/'/>
        <property name='file.name' value='/folk/wb/working_qf/vx692wb3322/r_r_wb16.12sp/docs/extensions/eclipse/plugins/com.windriver.ide.doc.wr_system_viewer_tooling_3.3'/>
      </repositoryProperties>
    </artifact>
    <artifact classifier='osgi.bundle' id='com.windriver.ide.doc.wr_mipc_2.2' version='2.2.0'>
      <properties size='2'>
        <property name='artifact.size' value='4096'/>
        <property name='download.size' value='4096'/>
      </properties>
      <repositoryProperties size='3'>
        <property name='artifact.folder' value='true'/>
        <property name='artifact.reference' value='file:/folk/wb/working_qf/vx692wb3322/r_r_wb16.12sp/docs/extensions/eclipse/plugins/com.windriver.ide.doc.wr_mipc_2.2/'/>
        <property name='file.name' value='/folk/wb/working_qf/vx692wb3322/r_r_wb16.12sp/docs/extensions/eclipse/plugins/com.windriver.ide.doc.wr_mipc_2.2'/>
      </repositoryProperties>
    </artifact>
    <artifact classifier='osgi.bundle' id='com.windriver.ide.doc.wr_workbench_data_monitor' version='3.3.0'>
      <properties size='2'>
        <property name='artifact.size' value='4096'/>
        <property name='download.size' value='4096'/>
      </properties>
      <repositoryProperties size='3'>
        <property name='artifact.folder' value='true'/>
        <property name='artifact.reference' value='file:/folk/wb/working_qf/vx692wb3322/r_r_wb16.12sp/docs/extensions/eclipse/plugins/com.windriver.ide.doc.wr_workbench_data_monitor_tooling_3.3/'/>
        <property name='file.name' value='/folk/wb/working_qf/vx692wb3322/r_r_wb16.12sp/docs/extensions/eclipse/plugins/com.windriver.ide.doc.wr_workbench_data_monitor_tooling_3.3'/>
      </repositoryProperties>
    </artifact>
    <artifact classifier='osgi.bundle' id='com.windriver.ide.doc.partners_generic_target_os' version='1.0.0'>
      <properties size='2'>
        <property name='artifact.size' value='4096'/>
        <property name='download.size' value='4096'/>
      </properties>
      <repositoryProperties size='3'>
        <property name='artifact.folder' value='true'/>
        <property name='artifact.reference' value='file:/folk/wb/working_qf/vx692wb3322/r_r_wb16.12sp/docs/extensions/eclipse/plugins/com.windriver.ide.doc.partners_generic_target_os/'/>
        <property name='file.name' value='/folk/wb/working_qf/vx692wb3322/r_r_wb16.12sp/docs/extensions/eclipse/plugins/com.windriver.ide.doc.partners_generic_target_os'/>
      </repositoryProperties>
    </artifact>
    <artifact classifier='osgi.bundle' id='com.windriver.ide.doc.partners.threadx' version='1.0.0'>
      <properties size='2'>
        <property name='artifact.size' value='4096'/>
        <property name='download.size' value='4096'/>
      </properties>
      <repositoryProperties size='3'>
        <property name='artifact.folder' value='true'/>
        <property name='artifact.reference' value='file:/folk/wb/working_qf/vx692wb3322/r_r_wb16.12sp/docs/extensions/eclipse/plugins/com.windriver.ide.doc.partners.threadx/'/>
        <property name='file.name' value='/folk/wb/working_qf/vx692wb3322/r_r_wb16.12sp/docs/extensions/eclipse/plugins/com.windriver.ide.doc.partners.threadx'/>
      </repositoryProperties>
    </artifact>
    <artifact classifier='osgi.bundle' id='com.windriver.ide.doc.vxworks' version='6.9.0'>
      <properties size='2'>
        <property name='artifact.size' value='4096'/>
        <property name='download.size' value='4096'/>
      </properties>
      <repositoryProperties size='3'>
        <property name='artifact.folder' value='true'/>
        <property name='artifact.reference' value='file:/folk/wb/working_qf/vx692wb3322/r_r_wb16.12sp/docs/extensions/eclipse/plugins/com.windriver.ide.doc.vxworks_tooling_6.9/'/>
        <property name='file.name' value='/folk/wb/working_qf/vx692wb3322/r_r_wb16.12sp/docs/extensions/eclipse/plugins/com.windriver.ide.doc.vxworks_tooling_6.9'/>
      </repositoryProperties>
    </artifact>
    <artifact classifier='osgi.bundle' id='com.windriver.ide.doc.wr_usb_2.7' version='2.7.0'>
      <properties size='2'>
        <property name='artifact.size' value='4096'/>
        <property name='download.size' value='4096'/>
      </properties>
      <repositoryProperties size='3'>
        <property name='artifact.folder' value='true'/>
        <property name='artifact.reference' value='file:/folk/wb/working_qf/vx692wb3322/r_r_wb16.12sp/docs/extensions/eclipse/plugins/com.windriver.ide.doc.wr_usb_2.7/'/>
        <property name='file.name' value='/folk/wb/working_qf/vx692wb3322/r_r_wb16.12sp/docs/extensions/eclipse/plugins/com.windriver.ide.doc.wr_usb_2.7'/>
      </repositoryProperties>
    </artifact>
    <artifact classifier='osgi.bundle' id='com.windriver.ide.doc.wr_gnu_compiler_4.3.3' version='4.3.3'>
      <properties size='2'>
        <property name='artifact.size' value='4096'/>
        <property name='download.size' value='4096'/>
      </properties>
      <repositoryProperties size='3'>
        <property name='artifact.folder' value='true'/>
        <property name='artifact.reference' value='file:/folk/wb/working_qf/vx692wb3322/r_r_wb16.12sp/docs/extensions/eclipse/plugins/com.windriver.ide.doc.wr_gnu_compiler_4.3.3/'/>
        <property name='file.name' value='/folk/wb/working_qf/vx692wb3322/r_r_wb16.12sp/docs/extensions/eclipse/plugins/com.windriver.ide.doc.wr_gnu_compiler_4.3.3'/>
      </repositoryProperties>
    </artifact>
    <artifact classifier='osgi.bundle' id='com.windriver.ide.doc.wr_workbench_ocd' version='3.3.0'>
      <properties size='2'>
        <property name='artifact.size' value='4096'/>
        <property name='download.size' value='4096'/>
      </properties>
      <repositoryProperties size='3'>
        <property name='artifact.folder' value='true'/>
        <property name='artifact.reference' value='file:/folk/wb/working_qf/vx692wb3322/r_r_wb16.12sp/docs/extensions/eclipse/plugins/com.windriver.ide.doc.wr_workbench_ocd_tooling_3.3/'/>
        <property name='file.name' value='/folk/wb/working_qf/vx692wb3322/r_r_wb16.12sp/docs/extensions/eclipse/plugins/com.windriver.ide.doc.wr_workbench_ocd_tooling_3.3'/>
      </repositoryProperties>
    </artifact>
    <artifact classifier='osgi.bundle' id='com.windriver.ide.doc.wr_workbench_performance_profiler' version='3.3.0'>
      <properties size='2'>
        <property name='artifact.size' value='4096'/>
        <property name='download.size' value='4096'/>
      </properties>
      <repositoryProperties size='3'>
        <property name='artifact.folder' value='true'/>
        <property name='artifact.reference' value='file:/folk/wb/working_qf/vx692wb3322/r_r_wb16.12sp/docs/extensions/eclipse/plugins/com.windriver.ide.doc.wr_workbench_performance_profiler_tooling_3.3/'/>
        <property name='file.name' value='/folk/wb/working_qf/vx692wb3322/r_r_wb16.12sp/docs/extensions/eclipse/plugins/com.windriver.ide.doc.wr_workbench_performance_profiler_tooling_3.3'/>
      </repositoryProperties>
    </artifact>
    <artifact classifier='osgi.bundle' id='com.windriver.ide.doc.wr_vx_simulator_6.9' version='6.9.0'>
      <properties size='2'>
        <property name='artifact.size' value='4096'/>
        <property name='download.size' value='4096'/>
      </properties>
      <repositoryProperties size='3'>
        <property name='artifact.folder' value='true'/>
        <property name='artifact.reference' value='file:/folk/wb/working_qf/vx692wb3322/r_r_wb16.12sp/docs/extensions/eclipse/plugins/com.windriver.ide.doc.wr_vx_simulator_6.9/'/>
        <property name='file.name' value='/folk/wb/working_qf/vx692wb3322/r_r_wb16.12sp/docs/extensions/eclipse/plugins/com.windriver.ide.doc.wr_vx_simulator_6.9'/>
      </repositoryProperties>
    </artifact>
    <artifact classifier='osgi.bundle' id='com.windriver.ide.doc.platform_general_vxworks_6.9' version='6.9.0'>
      <properties size='2'>
        <property name='artifact.size' value='4096'/>
        <property name='download.size' value='4096'/>
      </properties>
      <repositoryProperties size='3'>
        <property name='artifact.folder' value='true'/>
        <property name='artifact.reference' value='file:/folk/wb/working_qf/vx692wb3322/r_r_wb16.12sp/docs/extensions/eclipse/plugins/com.windriver.ide.doc.platform_general_vxworks_6.9/'/>
        <property name='file.name' value='/folk/wb/working_qf/vx692wb3322/r_r_wb16.12sp/docs/extensions/eclipse/plugins/com.windriver.ide.doc.platform_general_vxworks_6.9'/>
      </repositoryProperties>
    </artifact>
    <artifact classifier='osgi.bundle' id='com.windriver.ide.doc.standard_ccplus_libraries_6.9' version='6.9.0'>
      <properties size='2'>
        <property name='artifact.size' value='4096'/>
        <property name='download.size' value='4096'/>
      </properties>
      <repositoryProperties size='3'>
        <property name='artifact.folder' value='true'/>
        <property name='artifact.reference' value='file:/folk/wb/working_qf/vx692wb3322/r_r_wb16.12sp/docs/extensions/eclipse/plugins/com.windriver.ide.doc.standard_ccplus_libraries_6.9/'/>
        <property name='file.name' value='/folk/wb/working_qf/vx692wb3322/r_r_wb16.12sp/docs/extensions/eclipse/plugins/com.windriver.ide.doc.standard_ccplus_libraries_6.9'/>
      </repositoryProperties>
    </artifact>
    <artifact classifier='osgi.bundle' id='com.windriver.ide.doc.partners.ada' version='1.0.0'>
      <properties size='2'>
        <property name='artifact.size' value='4096'/>
        <property name='download.size' value='4096'/>
      </properties>
      <repositoryProperties size='3'>
        <property name='artifact.folder' value='true'/>
        <property name='artifact.reference' value='file:/folk/wb/working_qf/vx692wb3322/r_r_wb16.12sp/docs/extensions/eclipse/plugins/com.windriver.ide.doc.partners.ada/'/>
        <property name='file.name' value='/folk/wb/working_qf/vx692wb3322/r_r_wb16.12sp/docs/extensions/eclipse/plugins/com.windriver.ide.doc.partners.ada'/>
      </repositoryProperties>
    </artifact>
    <artifact classifier='osgi.bundle' id='com.windriver.ide.doc.platform_general_vxworks' version='6.9.0'>
      <properties size='2'>
        <property name='artifact.size' value='4096'/>
        <property name='download.size' value='4096'/>
      </properties>
      <repositoryProperties size='3'>
        <property name='artifact.folder' value='true'/>
        <property name='artifact.reference' value='file:/folk/wb/working_qf/vx692wb3322/r_r_wb16.12sp/docs/extensions/eclipse/plugins/com.windriver.ide.doc.platform_general_vxworks_tooling_6.9/'/>
        <property name='file.name' value='/folk/wb/working_qf/vx692wb3322/r_r_wb16.12sp/docs/extensions/eclipse/plugins/com.windriver.ide.doc.platform_general_vxworks_tooling_6.9'/>
      </repositoryProperties>
    </artifact>
    <artifact classifier='osgi.bundle' id='com.windriver.ide.doc.wr_workbench' version='3.3.0'>
      <properties size='2'>
        <property name='artifact.size' value='4096'/>
        <property name='download.size' value='4096'/>
      </properties>
      <repositoryProperties size='3'>
        <property name='artifact.folder' value='true'/>
        <property name='artifact.reference' value='file:/folk/wb/working_qf/vx692wb3322/r_r_wb16.12sp/docs/extensions/eclipse/plugins/com.windriver.ide.doc.wr_workbench_tooling_3.3/'/>
        <property name='file.name' value='/folk/wb/working_qf/vx692wb3322/r_r_wb16.12sp/docs/extensions/eclipse/plugins/com.windriver.ide.doc.wr_workbench_tooling_3.3'/>
      </repositoryProperties>
    </artifact>
    <artifact classifier='osgi.bundle' id='com.windriver.ide.doc.bsp_vxworks_6.9' version='6.9.0'>
      <properties size='2'>
        <property name='artifact.size' value='12288'/>
        <property name='download.size' value='12288'/>
      </properties>
      <repositoryProperties size='3'>
        <property name='artifact.folder' value='true'/>
        <property name='artifact.reference' value='file:/folk/wb/working_qf/vx692wb3322/r_r_wb16.12sp/docs/extensions/eclipse/plugins/com.windriver.ide.doc.bsp_vxworks_6.9/'/>
        <property name='file.name' value='/folk/wb/working_qf/vx692wb3322/r_r_wb16.12sp/docs/extensions/eclipse/plugins/com.windriver.ide.doc.bsp_vxworks_6.9'/>
      </repositoryProperties>
    </artifact>
    <artifact classifier='osgi.bundle' id='com.windriver.ide.doc.wr_net_stack_6.9' version='6.9.0'>
      <properties size='2'>
        <property name='artifact.size' value='4096'/>
        <property name='download.size' value='4096'/>
      </properties>
      <repositoryProperties size='3'>
        <property name='artifact.folder' value='true'/>
        <property name='artifact.reference' value='file:/folk/wb/working_qf/vx692wb3322/r_r_wb16.12sp/docs/extensions/eclipse/plugins/com.windriver.ide.doc.wr_net_stack_6.9/'/>
        <property name='file.name' value='/folk/wb/working_qf/vx692wb3322/r_r_wb16.12sp/docs/extensions/eclipse/plugins/com.windriver.ide.doc.wr_net_stack_6.9'/>
      </repositoryProperties>
    </artifact>
    <artifact classifier='osgi.bundle' id='com.windriver.ide.doc.intel_icc_12.0' version='12.0.0'>
      <properties size='2'>
        <property name='artifact.size' value='4096'/>
        <property name='download.size' value='4096'/>
      </properties>
      <repositoryProperties size='3'>
        <property name='artifact.folder' value='true'/>
        <property name='artifact.reference' value='file:/folk/wb/working_qf/vx692wb3322/r_r_wb16.12sp/docs/extensions/eclipse/plugins/com.windriver.ide.doc.intel_icc_12.0/'/>
        <property name='file.name' value='/folk/wb/working_qf/vx692wb3322/r_r_wb16.12sp/docs/extensions/eclipse/plugins/com.windriver.ide.doc.intel_icc_12.0'/>
      </repositoryProperties>
    </artifact>
    <artifact classifier='osgi.bundle' id='com.windriver.ide.doc.wr_workbench_code_coverage_analyzer' version='3.3.0'>
      <properties size='2'>
        <property name='artifact.size' value='4096'/>
        <property name='download.size' value='4096'/>
      </properties>
      <repositoryProperties size='3'>
        <property name='artifact.folder' value='true'/>
        <property name='artifact.reference' value='file:/folk/wb/working_qf/vx692wb3322/r_r_wb16.12sp/docs/extensions/eclipse/plugins/com.windriver.ide.doc.wr_workbench_code_coverage_analyzer_tooling_3.3/'/>
        <property name='file.name' value='/folk/wb/working_qf/vx692wb3322/r_r_wb16.12sp/docs/extensions/eclipse/plugins/com.windriver.ide.doc.wr_workbench_code_coverage_analyzer_tooling_3.3'/>
      </repositoryProperties>
    </artifact>
    <artifact classifier='osgi.bundle' id='com.windriver.ide.doc.wr_workbench_vxworks' version='3.3.0'>
      <properties size='2'>
        <property name='artifact.size' value='4096'/>
        <property name='download.size' value='4096'/>
      </properties>
      <repositoryProperties size='3'>
        <property name='artifact.folder' value='true'/>
        <property name='artifact.reference' value='file:/folk/wb/working_qf/vx692wb3322/r_r_wb16.12sp/docs/extensions/eclipse/plugins/com.windriver.ide.doc.wr_workbench_vxworks_tooling_3.3/'/>
        <property name='file.name' value='/folk/wb/working_qf/vx692wb3322/r_r_wb16.12sp/docs/extensions/eclipse/plugins/com.windriver.ide.doc.wr_workbench_vxworks_tooling_3.3'/>
      </repositoryProperties>
    </artifact>
  </artifacts>
</repository>
